pysigil/__init__.py
pysigil/__main__.py
pysigil/api.py
pysigil/authoring.py
pysigil/cli.py
pysigil/config.py
pysigil/core.py
pysigil/discovery.py
pysigil/errors.py
pysigil/io_config.py
pysigil/merge_policy.py
pysigil/orchestrator.py
pysigil/paths.py
pysigil/policy.py
pysigil/py.typed
pysigil/resolver.py
pysigil/root.py
pysigil/settings_metadata.py
pysigil/toolkit.py
pysigil/.sigil/settings.ini
pysigil/backends/__init__.py
pysigil/backends/base.py
pysigil/backends/ini_backend.py
pysigil/backends/json_backend.py
pysigil/backends/yaml_backend.py
pysigil/resources/__init__.py
pysigil/secrets/__init__.py
pysigil/ui/__init__.py
pysigil/ui/aurelia_theme.py
pysigil/ui/author_adapter.py
pysigil/ui/core.py
pysigil/ui/options_form.py
pysigil/ui/provider_adapter.py
pysigil/ui/scope_menu.py
pysigil/ui/sections.py
pysigil/ui/state.py
pysigil/ui/theme.py
pysigil/ui/value_parser.py
pysigil/ui/widgets.py
pysigil/ui/static/pysigil_ui_quick_reference.html
pysigil/ui/tk/__init__.py
pysigil/ui/tk/author.py
pysigil/ui/tk/author_tools.py
pysigil/ui/tk/config_gui.py
pysigil/ui/tk/dialogs.py
pysigil/ui/tk/list_editor.py
pysigil/ui/tk/rows.py
pysigil/ui/tk/widgets.py
pysigil-0.6.0.dist-info/licenses/AUTHORS_GUIDE.md
pysigil-0.6.0.dist-info/licenses/LICENSE
pysigil-0.6.0.dist-info/METADATA
pysigil-0.6.0.dist-info/WHEEL
pysigil-0.6.0.dist-info/entry_points.txt
pysigil-0.6.0.dist-info/top_level.txt
pysigil-0.6.0.dist-info/RECORD
