Metadata-Version: 2.4
Name: pysigil
Version: 0.6.0
Summary: Settings manager with layered scopes and tuple-key internals
Author: Tim Marquart
Requires-Python: >=3.10
License-File: LICENSE
License-File: AUTHORS_GUIDE.md
Requires-Dist: platformdirs>=4.0
Requires-Dist: tomlkit
Provides-Extra: json5
Requires-Dist: pyjson5>=1.6; extra == "json5"
Provides-Extra: gui
Provides-Extra: secrets
Requires-Dist: keyring>=25; extra == "secrets"
Provides-Extra: secrets-crypto
Requires-Dist: keyring>=25; extra == "secrets-crypto"
Requires-Dist: cryptography>=42; extra == "secrets-crypto"
Dynamic: license-file
